CHANGES.txt
LICENSE.txt
MANIFEST.in
README.txt
setup.py
js/__init__.py
js.jquery_qtip.egg-info/PKG-INFO
js.jquery_qtip.egg-info/SOURCES.txt
js.jquery_qtip.egg-info/dependency_links.txt
js.jquery_qtip.egg-info/entry_points.txt
js.jquery_qtip.egg-info/namespace_packages.txt
js.jquery_qtip.egg-info/not-zip-safe
js.jquery_qtip.egg-info/requires.txt
js.jquery_qtip.egg-info/top_level.txt
js/jquery_qtip/__init__.py
js/jquery_qtip/test_jquery.qtip.txt
js/jquery_qtip/resources/README.txt
js/jquery_qtip/resources/jquery.qtip.js
js/jquery_qtip/resources/jquery.qtip.min.js