Metadata-Version: 1.0
Name: js.jquery-qtip
Version: 1.0.0
Summary: Fanstatic packaging of jquery.qTip
Home-page: UNKNOWN
Author: Fanstatic Developers
Author-email: fanstatic@googlegroups.com
License: BSD
Platform: UNKNOWN
